LICENSE
README.rst
setup.py
mcmc_rebuild/__init__.py
mcmc_rebuild/acceptanceRules.py
mcmc_rebuild/basis.py
mcmc_rebuild/binaryPriors.py
mcmc_rebuild/changeBasis.py
mcmc_rebuild/energyFns.py
mcmc_rebuild/flipFns.py
mcmc_rebuild/generators.py
mcmc_rebuild/hyperparams.py
mcmc_rebuild/mcmc.py
mcmc_rebuild/mcmcLayers.py
mcmc_rebuild/measure.py
mcmc_rebuild/polyPrior.py
mcmc_rebuild/postProcess.py
mcmc_rebuild/samplers.py
mcmc_rebuild/serialize.py
mcmc_rebuild/updateRules.py
mcmc_rebuild/utils.py
nanomcmc/__init__.py
nanomcmc/acceptRule.py
nanomcmc/channel.py
nanomcmc/energyFns.py
nanomcmc/mcmc.py
nanomcmc/mcmcLayers.py
nanomcmc/proposer.py
nanomcmc/utils.py
nanomcmc.egg-info/PKG-INFO
nanomcmc.egg-info/SOURCES.txt
nanomcmc.egg-info/dependency_links.txt
nanomcmc.egg-info/not-zip-safe
nanomcmc.egg-info/requires.txt
nanomcmc.egg-info/top_level.txt
test/__init__.py
test/collect_timing.py
test/plot_collect_timing.py
test/t1_priors.py
test/test.py